{"password": "48a71434ba135c1f37d6952639b21ce9658861d4a0f0133c79694a9228487697", "Knows": {"MicrowavePhantoon": [false, 0], "GreenGateGlitch": [true, 10], "ScrewAttackExit": [false, 0], "WorstRoomIceCharge": [false, 0], "RedTowerClimb": [true, 50], "ShortCharge": [false, 0], "MockballWs": [false, 0], "MochtroidClip": [false, 0], "MidAirMorph": [true, 100], "CeilingDBoost": [false, 0], "AlcatrazEscape": [false, 0], "GetAroundWallJump": [true, 25], "TediousMountEverest": [false, 0], "SpringBallJumpFromWall": [false, 0], "ContinuousWallJump": [false, 0], "LavaDive": [false, 0], "HiJumpLessGauntletAccess": [false, 0], "SuitlessPuyoClip": [false, 0], "Mockball": [true, 5], "PreciousRoomXRayExit": [false, 0], "DraygonRoomCrystalFlash": [false, 0], "SuitlessSandpit": [false, 0], "SpongeBathSpeed": [true, 5], "MicrowaveDraygon": [false, 0], "Moondance": [false, 0], "PuyoClip": [false, 0], "SpongeBathHiJump": [true, 1], "SpongeBathBombJump": [false, 0], "DraygonRoomGrappleExit": [false, 0], "XrayDboost": [false, 0], "ReverseGateGlitch": [false, 0], "InfiniteBombJump": [true, 10], "SuitlessOuterMaridia": [false, 0], "GravLessLevel1": [false, 0], "GravityJump": [true, 10], "GravLessLevel3": [false, 0], "KillPlasmaPiratesWithCharge": [true, 5], "LavaDiveNoHiJump": [false, 0], "ShineSpark": [true, 100], "SpeedZebSkip": [false, 0], "KillPlasmaPiratesWithSpark": [false, 0], "SpringBallJump": [false, 0], "WallJump": [true, 100], "SimpleShortCharge": [true, 1], "DiagonalBombJump": [false, 0], "IceZebSkip": [false, 0], "GravLessLevel2": [false, 0], "GravLessLevel0": [true, 100], "HiJumpGauntletAccess": [false, 0], "EarlyKraid": [true, 1], "ReverseGateGlitchHiJumpLess": [false, 0], "DraygonGrappleKill": [true, 5]}, "Conf": {"itemsForbidden": [], "minorsPickup": {"Super": 5, "PowerBomb": 2, "Missile": 10}, "difficultyTarget": 1, "majorsPickup": "minimal"}, "Settings": {"Kraid": "Default", "MotherBrain": "Default", "hardRooms": {"Gauntlet": [[5, 10], [10, 5]], "X-Ray": [[10, 10], [14, 5]]}, "Phantoon": "A lot of trouble", "Ice": "No thanks", "Ridley": "I'm scared!", "MainUpperNorfair": "No thanks", "LowerNorfair": "Default", "bossesDifficulty": {"MotherBrain": {"Rate": 0.25, "Energy": {"4": 100, "8": 50, "12": 25, "16": 10, "20": 5, "24": 1}}, "Phantoon": {"Rate": 0.01, "Energy": {"1": 100, "3": 50, "4": 25, "5": 10, "7": 5, "10": 1}}, "Kraid": {"Rate": 0.015, "Energy": {"0.5": 10, "1.5": 5, "2.5": 1}}, "Ridley": {"Rate": 0.047, "Energy": {"1": 100, "11": 25, "20": 5, "14": 10, "7": 50}}, "Draygon": {"Rate": 0.025, "Energy": {"1": 100, "6": 50, "8": 25, "11": 10, "14": 5, "20": 1}}}, "Gauntlet": "Aarghh", "hellRuns": {"MainUpperNorfair": null, "LowerNorfair": null, "Ice": null}, "X-Ray": "Aarghh", "Draygon": "A lot of trouble"}}