{"score": 317, "Controller": {"A": "Jump", "B": "Dash", "Moonwalk": false, "L": "Angle Down", "R": "Angle Up", "Y": "Item Cancel", "X": "Shoot", "Select": "Item Select"}, "password": "365453a4dc558a8dc1e368684b360dc452792dea8614fa66e48deb52bb5edab1", "Knows": {"MicrowavePhantoon": [true, 1], "GreenGateGlitch": [true, 1], "NovaBoost": [true, 50], "ScrewAttackExit": [true, 5], "WorstRoomIceCharge": [true, 10], "RedTowerClimb": [true, 5], "ShortCharge": [true, 10], "MockballWs": [true, 5], "RonPopeilScrew": [false, 0], "MidAirMorph": [false, 0], "GravLessLevel1": [true, 5], "CeilingDBoost": [true, 1], "AlcatrazEscape": [true, 1], "GetAroundWallJump": [true, 1], "TediousMountEverest": [false, 0], "SpringBallJumpFromWall": [true, 5], "ContinuousWallJump": [true, 5], "LavaDive": [true, 5], "HiJumpLessGauntletAccess": [true, 1], "PuyoClipXRay": [true, 5], "Mockball": [true, 1], "PreciousRoomXRayExit": [true, 25], "LowGauntlet": [false, 0], "WallJumpCathedralExit": [true, 1], "SpongeBathSpeed": [true, 1], "MicrowaveDraygon": [true, 1], "Moondance": [false, 0], "HiJumpMamaTurtle": [false, 0], "SpeedZebSkip": [true, 5], "SpongeBathHiJump": [true, 1], "DraygonRoomGrappleExit": [true, 25], "SpongeBathBombJump": [true, 10], "SuitlessPuyoClip": [false, 0], "XrayDboost": [true, 5], "PuyoClip": [true, 10], "ReverseGateGlitch": [true, 1], "AccessSpringBallWithXRayClimb": [true, 25], "DraygonSparkKill": [true, 1], "AccessSpringBallWithBombJumps": [true, 10], "AccessSpringBallWithSpringBallBombJumps": [true, 5], "ReverseGateGlitchHiJumpLess": [true, 5], "DraygonRoomCrystalFlash": [true, 25], "GravityJump": [true, 1], "GravLessLevel3": [true, 50], "KillPlasmaPiratesWithCharge": [true, 1], "LavaDiveNoHiJump": [true, 100], "ShineSpark": [false, 0], "AccessSpringBallWithSpringBallJump": [true, 10], "NorfairReserveDBoost": [true, 5], "SnailClip": [true, 5], "KillPlasmaPiratesWithSpark": [true, 5], "SpringBallJump": [true, 5], "WallJump": [false, 0], "SimpleShortCharge": [true, 1], "DiagonalBombJump": [true, 5], "IceZebSkip": [true, 1], "CrocPBsDBoost": [true, 10], "GravLessLevel2": [true, 10], "CrocPBsIce": [true, 5], "MochtroidClip": [true, 1], "HiJumpGauntletAccess": [true, 1], "EarlyKraid": [true, 1], "IceMissileFromCroc": [true, 10], "InfiniteBombJump": [true, 1], "DraygonGrappleKill": [true, 1]}, "Settings": {"Kraid": "Quick Kill", "MainUpperNorfair": "Bring the heat", "Phantoon": "No problemo", "Ice": "Bring the heat", "Ridley": "Piece of cake", "MotherBrain": "Nice cutscene bro", "LowerNorfair": "Bring the heat", "Gauntlet": "Default", "X-Ray": "I don't mind spikes", "Draygon": "No problemo"}}